{"last_updated":"2026-05-22T14:31:27Z","account":{"id":"act_310500857276337","name":"ECF Consultoria","currency":"BRL"},"date_range":{"since":"2026-05-16","until":"2026-05-22"},"summary":{"spend":18757.84,"impressions":712710,"msgs":11,"leads":355,"purchases":29,"add_to_cart":98,"initiate_checkout":113,"lpv":5234,"link_clicks":10601,"cp_msg":1705.26,"cpl":52.84,"cpv":646.82,"cpm":26.32,"ctr":1.49,"lp_conv":3.35},"daily":[{"msgs":2,"leads":61,"purchases":0,"add_to_cart":14,"initiate_checkout":8,"lpv":1676,"link_clicks":3481,"cp_msg":2346.89,"cpl":76.95,"cpv":0,"date":"2026-05-16","spend":4693.78,"impressions":198945,"cpm":23.59,"ctr":2.14},{"msgs":0,"leads":70,"purchases":3,"add_to_cart":12,"initiate_checkout":11,"lpv":1542,"link_clicks":2874,"cp_msg":0,"cpl":64.97,"cpv":1515.89,"date":"2026-05-17","spend":4547.66,"impressions":163490,"cpm":27.82,"ctr":2.22},{"msgs":1,"leads":44,"purchases":4,"add_to_cart":16,"initiate_checkout":19,"lpv":746,"link_clicks":1393,"cp_msg":2988.23,"cpl":67.91,"cpv":747.06,"date":"2026-05-18","spend":2988.23,"impressions":143808,"cpm":20.78,"ctr":1.43},{"msgs":3,"leads":65,"purchases":9,"add_to_cart":13,"initiate_checkout":28,"lpv":732,"link_clicks":1436,"cp_msg":1158.74,"cpl":53.48,"cpv":386.25,"date":"2026-05-19","spend":3476.21,"impressions":114319,"cpm":30.41,"ctr":1.76},{"msgs":4,"leads":57,"purchases":3,"add_to_cart":17,"initiate_checkout":14,"lpv":233,"link_clicks":615,"cp_msg":373.78,"cpl":26.23,"cpv":498.37,"date":"2026-05-20","spend":1495.11,"impressions":44951,"cpm":33.26,"ctr":2.06},{"msgs":1,"leads":46,"purchases":8,"add_to_cart":23,"initiate_checkout":27,"lpv":248,"link_clicks":658,"cp_msg":1214.79,"cpl":26.41,"cpv":151.85,"date":"2026-05-21","spend":1214.79,"impressions":38100,"cpm":31.88,"ctr":2.38},{"msgs":0,"leads":12,"purchases":2,"add_to_cart":3,"initiate_checkout":6,"lpv":57,"link_clicks":144,"cp_msg":0,"cpl":28.5,"cpv":171.03,"date":"2026-05-22","spend":342.06,"impressions":9097,"cpm":37.6,"ctr":2.1}],"campaigns":[{"id":"120244212138750620","name":"[EVENTO PRESENCIAL MAGXP]  - [REMARKETING]","objective":"OUTCOME_SALES","status":"ACTIVE","daily":[{"msgs":0,"leads":0,"purchases":0,"add_to_cart":0,"initiate_checkout":1,"lpv":38,"link_clicks":62,"cp_msg":0,"cpl":0,"cpv":0,"date":"2026-05-16","spend":311.08,"impressions":5423,"cpm":57.36,"ctr":1.48},{"msgs":0,"leads":0,"purchases":0,"add_to_cart":0,"initiate_checkout":0,"lpv":54,"link_clicks":71,"cp_msg":0,"cpl":0,"cpv":0,"date":"2026-05-17","spend":277.23,"impressions":4775,"cpm":58.06,"ctr":1.78},{"msgs":0,"leads":0,"purchases":0,"add_to_cart":2,"initiate_checkout":4,"lpv":18,"link_clicks":20,"cp_msg":0,"cpl":0,"cpv":0,"date":"2026-05-18","spend":116.4,"impressions":2005,"cpm":58.05,"ctr":1.5},{"msgs":1,"leads":5,"purchases":7,"add_to_cart":2,"initiate_checkout":21,"lpv":135,"link_clicks":160,"cp_msg":554.09,"cpl":110.82,"cpv":79.16,"date":"2026-05-19","spend":554.09,"impressions":9975,"cpm":55.55,"ctr":2.17},{"msgs":0,"leads":1,"purchases":1,"add_to_cart":0,"initiate_checkout":5,"lpv":134,"link_clicks":169,"cp_msg":0,"cpl":566.57,"cpv":566.57,"date":"2026-05-20","spend":566.57,"impressions":11412,"cpm":49.65,"ctr":2.23},{"msgs":0,"leads":0,"purchases":3,"add_to_cart":1,"initiate_checkout":11,"lpv":68,"link_clicks":77,"cp_msg":0,"cpl":0,"cpv":71.95,"date":"2026-05-21","spend":215.86,"impressions":5917,"cpm":36.48,"ctr":1.98},{"msgs":0,"leads":0,"purchases":1,"add_to_cart":0,"initiate_checkout":3,"lpv":18,"link_clicks":19,"cp_msg":0,"cpl":0,"cpv":50.76,"date":"2026-05-22","spend":50.76,"impressions":1277,"cpm":39.75,"ctr":2.35}],"summary":{"msgs":1,"leads":6,"purchases":12,"add_to_cart":5,"initiate_checkout":45,"lpv":465,"link_clicks":578,"cp_msg":2091.99,"cpl":348.67,"cpv":174.33,"spend":2091.99,"impressions":40784,"cpm":51.29,"ctr":1.99,"lp_conv":1.04},"msgs":1,"leads":6,"purchases":12,"add_to_cart":5,"initiate_checkout":45,"lpv":465,"link_clicks":578,"cp_msg":2091.99,"cpl":348.67,"cpv":174.33,"spend":2091.99,"impressions":40784,"cpm":51.29,"ctr":1.99,"lp_conv":1.04},{"id":"120242102289220620","name":"[JOINVILLE S DO SUL + S BENTO DO SUL] - [VALIDAÇAO CRIATIVO]","objective":"OUTCOME_LEADS","status":"ACTIVE","daily":[{"msgs":0,"leads":16,"purchases":0,"add_to_cart":0,"initiate_checkout":0,"lpv":0,"link_clicks":137,"cp_msg":0,"cpl":21.59,"cpv":0,"date":"2026-05-16","spend":345.41,"impressions":13686,"cpm":25.24,"ctr":1.97},{"msgs":0,"leads":18,"purchases":0,"add_to_cart":0,"initiate_checkout":0,"lpv":0,"link_clicks":89,"cp_msg":0,"cpl":12.71,"cpv":0,"date":"2026-05-17","spend":228.82,"impressions":10220,"cpm":22.39,"ctr":1.99},{"msgs":0,"leads":4,"purchases":0,"add_to_cart":0,"initiate_checkout":0,"lpv":0,"link_clicks":45,"cp_msg":0,"cpl":39.27,"cpv":0,"date":"2026-05-18","spend":157.06,"impressions":7437,"cpm":21.12,"ctr":1.17},{"msgs":0,"leads":14,"purchases":0,"add_to_cart":0,"initiate_checkout":0,"lpv":2,"link_clicks":85,"cp_msg":0,"cpl":15.18,"cpv":0,"date":"2026-05-19","spend":212.56,"impressions":9733,"cpm":21.84,"ctr":1.61},{"msgs":1,"leads":16,"purchases":0,"add_to_cart":0,"initiate_checkout":0,"lpv":0,"link_clicks":82,"cp_msg":211.92,"cpl":13.24,"cpv":0,"date":"2026-05-20","spend":211.92,"impressions":10211,"cpm":20.75,"ctr":1.56},{"msgs":0,"leads":14,"purchases":0,"add_to_cart":0,"initiate_checkout":0,"lpv":0,"link_clicks":72,"cp_msg":0,"cpl":15.32,"cpv":0,"date":"2026-05-21","spend":214.54,"impressions":10393,"cpm":20.64,"ctr":1.45},{"msgs":0,"leads":4,"purchases":0,"add_to_cart":0,"initiate_checkout":0,"lpv":0,"link_clicks":18,"cp_msg":0,"cpl":12.82,"cpv":0,"date":"2026-05-22","spend":51.28,"impressions":2131,"cpm":24.06,"ctr":1.64}],"summary":{"msgs":1,"leads":86,"purchases":0,"add_to_cart":0,"initiate_checkout":0,"lpv":2,"link_clicks":528,"cp_msg":1421.59,"cpl":16.53,"cpv":0,"spend":1421.59,"impressions":63811,"cpm":22.28,"ctr":1.66,"lp_conv":16.29},"msgs":1,"leads":86,"purchases":0,"add_to_cart":0,"initiate_checkout":0,"lpv":2,"link_clicks":528,"cp_msg":1421.59,"cpl":16.53,"cpv":0,"spend":1421.59,"impressions":63811,"cpm":22.28,"ctr":1.66,"lp_conv":16.29},{"id":"120238546111100620","name":"[POLOS ARAPONGAS] - [16/01]","objective":"OUTCOME_LEADS","status":"ACTIVE","daily":[{"msgs":0,"leads":10,"purchases":0,"add_to_cart":0,"initiate_checkout":0,"lpv":0,"link_clicks":143,"cp_msg":0,"cpl":34.47,"cpv":0,"date":"2026-05-16","spend":344.68,"impressions":13235,"cpm":26.04,"ctr":1.59},{"msgs":0,"leads":12,"purchases":0,"add_to_cart":0,"initiate_checkout":0,"lpv":0,"link_clicks":103,"cp_msg":0,"cpl":18.07,"cpv":0,"date":"2026-05-17","spend":216.78,"impressions":7573,"cpm":28.63,"ctr":2.06},{"msgs":0,"leads":1,"purchases":0,"add_to_cart":0,"initiate_checkout":0,"lpv":2,"link_clicks":57,"cp_msg":0,"cpl":131.52,"cpv":0,"date":"2026-05-18","spend":131.52,"impressions":4208,"cpm":31.25,"ctr":1.9},{"msgs":0,"leads":11,"purchases":0,"add_to_cart":0,"initiate_checkout":0,"lpv":1,"link_clicks":130,"cp_msg":0,"cpl":18.83,"cpv":0,"date":"2026-05-19","spend":207.14,"impressions":8186,"cpm":25.3,"ctr":2.09},{"msgs":0,"leads":8,"purchases":0,"add_to_cart":0,"initiate_checkout":0,"lpv":1,"link_clicks":131,"cp_msg":0,"cpl":28.77,"cpv":0,"date":"2026-05-20","spend":230.16,"impressions":9427,"cpm":24.41,"ctr":1.82},{"msgs":0,"leads":7,"purchases":0,"add_to_cart":0,"initiate_checkout":0,"lpv":2,"link_clicks":143,"cp_msg":0,"cpl":28.37,"cpv":0,"date":"2026-05-21","spend":198.57,"impressions":7042,"cpm":28.2,"ctr":2.61},{"msgs":0,"leads":1,"purchases":0,"add_to_cart":0,"initiate_checkout":0,"lpv":0,"link_clicks":22,"cp_msg":0,"cpl":54.21,"cpv":0,"date":"2026-05-22","spend":54.21,"impressions":1449,"cpm":37.41,"ctr":1.93}],"summary":{"msgs":0,"leads":50,"purchases":0,"add_to_cart":0,"initiate_checkout":0,"lpv":6,"link_clicks":729,"cp_msg":0,"cpl":27.66,"cpv":0,"spend":1383.06,"impressions":51120,"cpm":27.06,"ctr":1.96,"lp_conv":6.86},"msgs":0,"leads":50,"purchases":0,"add_to_cart":0,"initiate_checkout":0,"lpv":6,"link_clicks":729,"cp_msg":0,"cpl":27.66,"cpv":0,"spend":1383.06,"impressions":51120,"cpm":27.06,"ctr":1.96,"lp_conv":6.86},{"id":"120241881649680620","name":"[CBO] - [POLOS SJRP]","objective":"OUTCOME_LEADS","status":"ACTIVE","daily":[{"msgs":0,"leads":7,"purchases":0,"add_to_cart":0,"initiate_checkout":0,"lpv":2,"link_clicks":62,"cp_msg":0,"cpl":34.51,"cpv":0,"date":"2026-05-16","spend":241.56,"impressions":7026,"cpm":34.38,"ctr":1.42},{"msgs":0,"leads":8,"purchases":0,"add_to_cart":0,"initiate_checkout":0,"lpv":0,"link_clicks":63,"cp_msg":0,"cpl":20.13,"cpv":0,"date":"2026-05-17","spend":161.06,"impressions":4306,"cpm":37.4,"ctr":2.16},{"msgs":0,"leads":6,"purchases":0,"add_to_cart":0,"initiate_checkout":0,"lpv":0,"link_clicks":34,"cp_msg":0,"cpl":18.3,"cpv":0,"date":"2026-05-18","spend":109.78,"impressions":3152,"cpm":34.83,"ctr":1.74},{"msgs":0,"leads":3,"purchases":0,"add_to_cart":0,"initiate_checkout":0,"lpv":0,"link_clicks":35,"cp_msg":0,"cpl":47.36,"cpv":0,"date":"2026-05-19","spend":142.09,"impressions":4783,"cpm":29.71,"ctr":1.11},{"msgs":0,"leads":4,"purchases":0,"add_to_cart":0,"initiate_checkout":0,"lpv":1,"link_clicks":36,"cp_msg":0,"cpl":34.75,"cpv":0,"date":"2026-05-20","spend":139.0,"impressions":4558,"cpm":30.5,"ctr":1.27},{"msgs":1,"leads":5,"purchases":0,"add_to_cart":0,"initiate_checkout":0,"lpv":1,"link_clicks":29,"cp_msg":141.62,"cpl":28.32,"cpv":0,"date":"2026-05-21","spend":141.62,"impressions":3743,"cpm":37.84,"ctr":1.34},{"msgs":0,"leads":2,"purchases":0,"add_to_cart":0,"initiate_checkout":0,"lpv":0,"link_clicks":11,"cp_msg":0,"cpl":21.78,"cpv":0,"date":"2026-05-22","spend":43.56,"impressions":1054,"cpm":41.33,"ctr":1.8}],"summary":{"msgs":1,"leads":35,"purchases":0,"add_to_cart":0,"initiate_checkout":0,"lpv":4,"link_clicks":270,"cp_msg":978.67,"cpl":27.96,"cpv":0,"spend":978.67,"impressions":28622,"cpm":34.19,"ctr":1.5,"lp_conv":12.96},"msgs":1,"leads":35,"purchases":0,"add_to_cart":0,"initiate_checkout":0,"lpv":4,"link_clicks":270,"cp_msg":978.67,"cpl":27.96,"cpv":0,"spend":978.67,"impressions":28622,"cpm":34.19,"ctr":1.5,"lp_conv":12.96},{"id":"120239522595750620","name":"[Bento Gonçalves + SERRA G CBO] - [VALIDAÇAO CRIATIVO]","objective":"OUTCOME_LEADS","status":"ACTIVE","daily":[{"msgs":0,"leads":5,"purchases":0,"add_to_cart":0,"initiate_checkout":0,"lpv":0,"link_clicks":75,"cp_msg":0,"cpl":48.58,"cpv":0,"date":"2026-05-16","spend":242.88,"impressions":6784,"cpm":35.8,"ctr":1.87},{"msgs":0,"leads":3,"purchases":0,"add_to_cart":0,"initiate_checkout":0,"lpv":0,"link_clicks":56,"cp_msg":0,"cpl":49.46,"cpv":0,"date":"2026-05-17","spend":148.39,"impressions":4613,"cpm":32.17,"ctr":1.86},{"msgs":0,"leads":4,"purchases":0,"add_to_cart":0,"initiate_checkout":0,"lpv":1,"link_clicks":29,"cp_msg":0,"cpl":26.66,"cpv":0,"date":"2026-05-18","spend":106.64,"impressions":3345,"cpm":31.88,"ctr":1.7},{"msgs":0,"leads":6,"purchases":0,"add_to_cart":0,"initiate_checkout":0,"lpv":1,"link_clicks":61,"cp_msg":0,"cpl":23.81,"cpv":0,"date":"2026-05-19","spend":142.85,"impressions":5241,"cpm":27.26,"ctr":1.89},{"msgs":0,"leads":7,"purchases":0,"add_to_cart":0,"initiate_checkout":0,"lpv":0,"link_clicks":55,"cp_msg":0,"cpl":20.73,"cpv":0,"date":"2026-05-20","spend":145.13,"impressions":5308,"cpm":27.34,"ctr":2.05},{"msgs":0,"leads":4,"purchases":0,"add_to_cart":0,"initiate_checkout":0,"lpv":0,"link_clicks":60,"cp_msg":0,"cpl":37.12,"cpv":0,"date":"2026-05-21","spend":148.5,"impressions":5135,"cpm":28.92,"ctr":1.83},{"msgs":0,"leads":0,"purchases":0,"add_to_cart":0,"initiate_checkout":0,"lpv":0,"link_clicks":10,"cp_msg":0,"cpl":0,"cpv":0,"date":"2026-05-22","spend":36.59,"impressions":1136,"cpm":32.21,"ctr":1.32}],"summary":{"msgs":0,"leads":29,"purchases":0,"add_to_cart":0,"initiate_checkout":0,"lpv":2,"link_clicks":346,"cp_msg":0,"cpl":33.48,"cpv":0,"spend":970.98,"impressions":31562,"cpm":30.76,"ctr":1.86,"lp_conv":8.38},"msgs":0,"leads":29,"purchases":0,"add_to_cart":0,"initiate_checkout":0,"lpv":2,"link_clicks":346,"cp_msg":0,"cpl":33.48,"cpv":0,"spend":970.98,"impressions":31562,"cpm":30.76,"ctr":1.86,"lp_conv":8.38},{"id":"120244759585200620","name":"[EVENTO PRESENCIAL MAG XP I.A] - [SÃO PAULO]","objective":"OUTCOME_SALES","status":"ACTIVE","daily":[{"msgs":1,"leads":0,"purchases":0,"add_to_cart":0,"initiate_checkout":0,"lpv":53,"link_clicks":86,"cp_msg":113.3,"cpl":0,"cpv":0,"date":"2026-05-20","spend":113.3,"impressions":2283,"cpm":49.63,"ctr":3.99},{"msgs":0,"leads":1,"purchases":1,"add_to_cart":1,"initiate_checkout":6,"lpv":108,"link_clicks":183,"cp_msg":0,"cpl":212.64,"cpv":212.64,"date":"2026-05-21","spend":212.64,"impressions":4224,"cpm":50.34,"ctr":4.62},{"msgs":0,"leads":0,"purchases":0,"add_to_cart":0,"initiate_checkout":1,"lpv":25,"link_clicks":48,"cp_msg":0,"cpl":0,"cpv":0,"date":"2026-05-22","spend":81.37,"impressions":1589,"cpm":51.21,"ctr":2.89}],"summary":{"msgs":1,"leads":1,"purchases":1,"add_to_cart":1,"initiate_checkout":7,"lpv":186,"link_clicks":317,"cp_msg":407.31,"cpl":407.31,"cpv":407.31,"spend":407.31,"impressions":8096,"cpm":50.31,"ctr":4.1,"lp_conv":0.32},"msgs":1,"leads":1,"purchases":1,"add_to_cart":1,"initiate_checkout":7,"lpv":186,"link_clicks":317,"cp_msg":407.31,"cpl":407.31,"cpv":407.31,"spend":407.31,"impressions":8096,"cpm":50.31,"ctr":4.1,"lp_conv":0.32},{"id":"120243549705150620","name":"[GESTÃO ADS] - [ABO]  - [VALIDAÇÃO]","objective":"OUTCOME_LEADS","status":"ACTIVE","daily":[{"msgs":0,"leads":4,"purchases":0,"add_to_cart":1,"initiate_checkout":0,"lpv":14,"link_clicks":17,"cp_msg":0,"cpl":16.33,"cpv":0,"date":"2026-05-16","spend":65.31,"impressions":949,"cpm":68.82,"ctr":2.85},{"msgs":0,"leads":2,"purchases":1,"add_to_cart":2,"initiate_checkout":0,"lpv":16,"link_clicks":18,"cp_msg":0,"cpl":25.25,"cpv":50.5,"date":"2026-05-17","spend":50.5,"impressions":879,"cpm":57.45,"ctr":2.73},{"msgs":0,"leads":2,"purchases":0,"add_to_cart":2,"initiate_checkout":0,"lpv":18,"link_clicks":19,"cp_msg":0,"cpl":22.14,"cpv":0,"date":"2026-05-18","spend":44.28,"impressions":835,"cpm":53.03,"ctr":2.75},{"msgs":0,"leads":0,"purchases":0,"add_to_cart":2,"initiate_checkout":0,"lpv":26,"link_clicks":31,"cp_msg":0,"cpl":0,"cpv":0,"date":"2026-05-19","spend":45.66,"impressions":776,"cpm":58.84,"ctr":5.54},{"msgs":0,"leads":6,"purchases":0,"add_to_cart":4,"initiate_checkout":0,"lpv":17,"link_clicks":23,"cp_msg":0,"cpl":6.72,"cpv":0,"date":"2026-05-20","spend":40.32,"impressions":823,"cpm":48.99,"ctr":4.13},{"msgs":0,"leads":4,"purchases":0,"add_to_cart":7,"initiate_checkout":0,"lpv":49,"link_clicks":65,"cp_msg":0,"cpl":10.29,"cpv":0,"date":"2026-05-21","spend":41.16,"impressions":800,"cpm":51.45,"ctr":9.0},{"msgs":0,"leads":0,"purchases":0,"add_to_cart":0,"initiate_checkout":0,"lpv":10,"link_clicks":12,"cp_msg":0,"cpl":0,"cpv":0,"date":"2026-05-22","spend":16.69,"impressions":308,"cpm":54.19,"ctr":4.22}],"summary":{"msgs":0,"leads":18,"purchases":1,"add_to_cart":18,"initiate_checkout":0,"lpv":150,"link_clicks":185,"cp_msg":0,"cpl":16.88,"cpv":303.92,"spend":303.92,"impressions":5370,"cpm":56.6,"ctr":4.39,"lp_conv":9.73},"msgs":0,"leads":18,"purchases":1,"add_to_cart":18,"initiate_checkout":0,"lpv":150,"link_clicks":185,"cp_msg":0,"cpl":16.88,"cpv":303.92,"spend":303.92,"impressions":5370,"cpm":56.6,"ctr":4.39,"lp_conv":9.73},{"id":"120241197873910620","name":"[CBO META DE CUSTO] - [LIVE 10 EM 7] - [CRIATIVOS SECUNDÁRIOS]","objective":"OUTCOME_SALES","status":"ACTIVE","daily":[{"msgs":0,"leads":5,"purchases":0,"add_to_cart":12,"initiate_checkout":4,"lpv":17,"link_clicks":19,"cp_msg":0,"cpl":4.25,"cpv":0,"date":"2026-05-16","spend":21.23,"impressions":522,"cpm":40.67,"ctr":5.94},{"msgs":0,"leads":7,"purchases":2,"add_to_cart":8,"initiate_checkout":3,"lpv":18,"link_clicks":23,"cp_msg":0,"cpl":3.79,"cpv":13.25,"date":"2026-05-17","spend":26.5,"impressions":574,"cpm":46.17,"ctr":7.32},{"msgs":0,"leads":11,"purchases":2,"add_to_cart":10,"initiate_checkout":6,"lpv":20,"link_clicks":23,"cp_msg":0,"cpl":2.46,"cpv":13.51,"date":"2026-05-18","spend":27.02,"impressions":649,"cpm":41.63,"ctr":4.47},{"msgs":0,"leads":7,"purchases":1,"add_to_cart":9,"initiate_checkout":5,"lpv":17,"link_clicks":21,"cp_msg":0,"cpl":4.64,"cpv":32.45,"date":"2026-05-19","spend":32.45,"impressions":631,"cpm":51.43,"ctr":4.75},{"msgs":1,"leads":10,"purchases":2,"add_to_cart":13,"initiate_checkout":9,"lpv":25,"link_clicks":33,"cp_msg":48.71,"cpl":4.87,"cpv":24.36,"date":"2026-05-20","spend":48.71,"impressions":929,"cpm":52.43,"ctr":5.38},{"msgs":0,"leads":10,"purchases":4,"add_to_cart":14,"initiate_checkout":10,"lpv":19,"link_clicks":29,"cp_msg":0,"cpl":4.19,"cpv":10.47,"date":"2026-05-21","spend":41.9,"impressions":846,"cpm":49.53,"ctr":4.96},{"msgs":0,"leads":4,"purchases":1,"add_to_cart":3,"initiate_checkout":2,"lpv":4,"link_clicks":4,"cp_msg":0,"cpl":1.9,"cpv":7.6,"date":"2026-05-22","spend":7.6,"impressions":153,"cpm":49.67,"ctr":3.27}],"summary":{"msgs":1,"leads":54,"purchases":12,"add_to_cart":69,"initiate_checkout":39,"lpv":120,"link_clicks":152,"cp_msg":205.41,"cpl":3.8,"cpv":17.12,"spend":205.41,"impressions":4304,"cpm":47.73,"ctr":5.32,"lp_conv":35.53},"msgs":1,"leads":54,"purchases":12,"add_to_cart":69,"initiate_checkout":39,"lpv":120,"link_clicks":152,"cp_msg":205.41,"cpl":3.8,"cpv":17.12,"spend":205.41,"impressions":4304,"cpm":47.73,"ctr":5.32,"lp_conv":35.53}],"ads":[{"id":"120242102289260620","name":"CRIATIVO3","campaign_id":"120242102289220620","campaign_name":"[JOINVILLE S DO SUL + S BENTO DO SUL] - [VALIDAÇAO CRIATIVO]","adset":"","thumbnail":"https://scontent-lhr8-1.xx.fbcdn.net/v/t15.5256-10/657526155_1276687064528179_4095989870540439219_n.jpg?_nc_cat=107&ccb=1-7&_nc_ohc=myrNHdoadEkQ7kNvwHuJqbj&_nc_oc=Adp7Ux2pO2JnpQ0avwPxlPrYdAMPEStv2DgXlbKZMsRe7XpZ4_7r2K1sLzSOqw62oV0&_nc_zt=23&_nc_ht=scontent-lhr8-1.xx&edm=AOgd6ZUEAAAA&_nc_gid=f2mTQQnWU4Aozu9icrgzMQ&_nc_tpa=Q5bMBQH-zPNVWo0TJX1Jl_XlPxl-IndK1YyQhmS_KYsi2iqSYRf867h1RhOfvTu8KFgoZEEmWesvKjUNOg&stp=c0.5000x0.5000f_dst-emg0_p64x64_q75_tt6&ur=5fad0e&_nc_sid=58080a&oh=00_Af6v6baMizYwuVUdMFyLUtm9zPmwinoSDjAeheTXJdT21Q&oe=6A164A04","preview_url":"https://business.facebook.com/ads/api/preview_iframe.php?d=AQIz90CN6grhtbQGaQ8w-OylneNXWfztMjfrPTvPrO90DkNSVjnrZCBx8ZHt-e07zX6x6n7_x4V_g2y_xVydhsliV2YcBpunIhAiPb8tgVqt8pLkBpjj78tlFPHaY6sDAQ-bsTIsj2fTlISTRwAlmlf102w1lhbITEElWwhIer2d2rfxP0YYoQlabpVWs0Fhh013CHAXIj31aN43umsjKoJd80sHzB3Pdv8qnLLuBXGDRGbbfqRgKi7kD-kymDVMFS39Mux1Osr9l7kAd4T2q9Jt32cY35cj6VFxMg-P_kEPNmDUt25QnCZyicA_odPK2MpKAhi549eCTihopXRBEjYStG8CvizNTtZDIYOHyAeAlhe5GKekyxgDS6biBkfhtT_ei9vRMjvcMrSM4vi3OjH8bQx0K56BHL9p8CRO_ScXRxfccf1eHgwPCAYQSYHkgWA&t=AQJkNOY8bQo_05NyuOg","active":true,"msgs":1,"leads":84,"purchases":0,"add_to_cart":0,"initiate_checkout":0,"lpv":2,"link_clicks":518,"cp_msg":1404.7,"cpl":16.72,"cpv":0,"spend":1404.7,"impressions":63154,"cpm":22.24,"ctr":1.65},{"id":"120238547419950620","name":"CRIATIVO 3","campaign_id":"120238546111100620","campaign_name":"[POLOS ARAPONGAS] - [16/01]","adset":"","thumbnail":"https://scontent-lhr6-1.xx.fbcdn.net/v/t15.5256-10/615706573_1100895488743779_9031200008434492053_n.jpg?_nc_cat=102&ccb=1-7&_nc_ohc=nppkzoTAVLcQ7kNvwF5tzH_&_nc_oc=AdrJkNtveyBK4W4pIhVSrDwre6E5Xc8bS1wnvLSExrMGn4Kd7rEjgRD2QFLCt7uQ8IE&_nc_zt=23&_nc_ht=scontent-lhr6-1.xx&edm=AOgd6ZUEAAAA&_nc_gid=f2mTQQnWU4Aozu9icrgzMQ&_nc_tpa=Q5bMBQEFxVkHdV-I7JpGLJBgQjv-usLSJkRi6sO5-CNNZ3rIh17YDxfn_byQeL7T3OsIgshovDUsuAgBjw&stp=c0.5000x0.5000f_dst-emg0_p64x64_q75_tt6&ur=5fad0e&_nc_sid=58080a&oh=00_Af6ds16tp5l7gD4K-BR73c273lxTFJPly-vldn3rwpQnOA&oe=6A1655C7","preview_url":"https://business.facebook.com/ads/api/preview_iframe.php?d=AQL5dr5cM_5mHJZsgeIBJWRNxIB79t2Ylpf-YufYWLxtv9pbLmEqOLyhP95NDfUoiCe_D5FurjJU-zzhpINNpR1XTi1GhS6YBdbL9ICr3V68ds0jf2FgeaFD5K_Gkk_VRhd8hlynYrf6WstSXXEmrPLQSjynilkCQ8J0IGGl-8YpyT_z2HpQLuvyohNzaa8Ixgv989FLUZy1iuQRhZTnesII9jdv-UF6PETw3birZ3hew2UDqkqcUyVLnrtC9HSV6aPAVRbhYNBWFkWbZAtnkBEdxkLHRUwKTV4uItQRkM8BjTEZIdAuGChrNV7EBeNisH852fE3NcxROEspwa7lF-UP9yVNs9Riv-Jt9XzzsUWnUGIthpUz-rsK0NPvd8PUEyWrmmd0cIkGM9RwxdvEjd9e3e_RlBwg7JuHs1cSg6H60gRAFZO3wKlIEaunadPcKbQ&t=AQJ3p1NdQnvYgPWJVLg","active":true,"msgs":0,"leads":47,"purchases":0,"add_to_cart":0,"initiate_checkout":0,"lpv":6,"link_clicks":720,"cp_msg":0,"cpl":28.07,"cpv":0,"spend":1319.41,"impressions":48156,"cpm":27.4,"ctr":2.04},{"id":"120239522614740620","name":"CRIATIVO V8 — esse","campaign_id":"120239522595750620","campaign_name":"[Bento Gonçalves + SERRA G CBO] - [VALIDAÇAO CRIATIVO]","adset":"","thumbnail":"https://scontent-lhr8-2.xx.fbcdn.net/v/t15.5256-10/625340168_891791743596046_4278733430937368687_n.jpg?_nc_cat=106&ccb=1-7&_nc_ohc=yrIRfztSZrAQ7kNvwFsJ0h7&_nc_oc=AdpIn4zCGEGo2ZNiJDADnjzowbsg714FmJRzoboEKFzUUk2TvYMuwl3i-VrLJeOipPM&_nc_zt=23&_nc_ht=scontent-lhr8-2.xx&edm=AOgd6ZUEAAAA&_nc_gid=f2mTQQnWU4Aozu9icrgzMQ&_nc_tpa=Q5bMBQEOf5K5k3YeDM0yGkqEQL_x3K278IGpwqDDudDJifgZmyxboykuscdnh3frnRyuCe0RDZh86KGtvA&stp=c0.5000x0.5000f_dst-emg0_p64x64_q75_tt6&ur=5fad0e&_nc_sid=58080a&oh=00_Af68t0JqJyq4xIU7-jawyPEV-5kbCjz9i6Yxvl_EhpC1UQ&oe=6A16263A","preview_url":"https://business.facebook.com/ads/api/preview_iframe.php?d=AQINAZbKsaLp-Kjm4AmqVLfZ8gSCODMCF5hTSftqKUKyzTBE-s9BrcUONYDuf0N1GIzwjs7RDCN5jHe4w14Kzmjj4cvIJGjp81k6L_2uCKxu1gIKGevIGqBotdYENNe3sFEaCnGSZE2gHxnKGAmagqiIUbyUzEC2akVQSfPltI-OvqoacuRQKbPNQ2SjjfZVy0Qe7fdAT0GqW_S5oxVJTW6WDXztCIEfTMe1Es9PIdPb2ue7CcpaWFfq0pCqbih_73oLjpRuWF1v_R1LagO1bfJybi_i1yXq8yIWTWxZnNXiNr2A4n5NiJ5H1nkOE_AJXg4d59S1CTqOScim-D5BNv390fF_ddjDVVnSTyVKM0Abc3YayW293qacPTk0LL1w9Tl5BR_plevrMhJ4pQ1B0h4F1ZQXFNOlqCaiSXtICFsk_i1jWwcFyDt8J63a8-l2HOc&t=AQKmkyVfYKumxKo4l7k","active":true,"msgs":0,"leads":29,"purchases":0,"add_to_cart":0,"initiate_checkout":0,"lpv":2,"link_clicks":331,"cp_msg":0,"cpl":32.24,"cpv":0,"spend":935.0,"impressions":29851,"cpm":31.32,"ctr":1.9},{"id":"120241882122780620","name":"CRIATIVO 2","campaign_id":"120241881649680620","campaign_name":"[CBO] - [POLOS SJRP]","adset":"","thumbnail":"https://scontent-lhr6-2.xx.fbcdn.net/v/t15.5256-10/663353453_1616431912809967_8865566238118576285_n.jpg?_nc_cat=104&ccb=1-7&_nc_ohc=jgNUQxDuGFAQ7kNvwHc7xZd&_nc_oc=AdpihVSXPm658FJ-iKpZ04m0U9jRxsiK7MywqGlfhwBmc9QYRYkidMMhQWqIcOuh2lc&_nc_zt=23&_nc_ht=scontent-lhr6-2.xx&edm=AOgd6ZUEAAAA&_nc_gid=f2mTQQnWU4Aozu9icrgzMQ&_nc_tpa=Q5bMBQGXnAlgB3XZK2wnUsYaq0ZTjMp8klepS0LZyVap-XxHq5hKJOtfg6DCo9mOsEgUZlFBYDTTA8UqQg&stp=c0.5000x0.5000f_dst-emg0_p64x64_q75_tt6&ur=5fad0e&_nc_sid=58080a&oh=00_Af5z67xbFVu53jfXLR-Zbtg4-XtSWm0zELrBFXAH8UdeKA&oe=6A163FFC","preview_url":"https://business.facebook.com/ads/api/preview_iframe.php?d=AQJQ-TwjizsFrtAMWR8Rp_zsKwN5tBmBAhEZOwfXINKJL_YVxPH2N0kf-lM-nfQ5-lqSBxYUhOpd--Yvy55Hrm5H0QhBO0xoUSX8-hJiVjYSW1uEVcs-ILu7iPb2Ugs67TP2SNU2kM9_NYfXo4Gq7q8fII4PcAj4bMXwwqmfZ09ylUJ5cgnLgXXS0NjMR-FjbRSwdtsoqOq43GH-HqBu6r-vFOuAlm6CtSAZUr5HoW7lbQ1iv48NyvP9NbbYDxHiEqkeGRcLXXahIUI673_tpK7MhCeUmeWNGOm_JefPFWW9hRQKAb2oNe4kLouL8YMkVPWhrG1kiy-1zlSlVciqKgOFXjBsPU5TKnfFj_o26ae8R9H3Nk4T8fh5vTyK4JC3EKZc0xu-OmJdQk5iWVbtvncREYI6_KRfLQ9acanFmj25ZRM-MNEjr4MgC0k__dIl2wg&t=AQLaq3ey7fNH9P_DXkw","active":true,"msgs":1,"leads":32,"purchases":0,"add_to_cart":0,"initiate_checkout":0,"lpv":4,"link_clicks":242,"cp_msg":872.81,"cpl":27.28,"cpv":0,"spend":872.81,"impressions":25573,"cpm":34.13,"ctr":1.5},{"id":"120244682559520620","name":"3_VD - pag nova","campaign_id":"120244212138750620","campaign_name":"[EVENTO PRESENCIAL MAGXP]  - [REMARKETING]","adset":"","thumbnail":"https://scontent-lhr6-1.xx.fbcdn.net/v/t15.5256-10/701206881_2464181520692600_3234061015611966697_n.jpg?_nc_cat=110&ccb=1-7&_nc_ohc=yJe0D65JdcAQ7kNvwHnjClD&_nc_oc=AdpJWztWJteiWZte6m6wLaCl1MlghVpkraB3van2oig4AEgVokSK6falGmqdeGdciFE&_nc_zt=23&_nc_ht=scontent-lhr6-1.xx&edm=AOgd6ZUEAAAA&_nc_gid=f2mTQQnWU4Aozu9icrgzMQ&_nc_tpa=Q5bMBQEy5BULlXl012usI61zExXZkDd8PAkKeEcFxQ1vrIJwpY4u0bCVjgsI4UR2BkT6CuQAmHRiubSo5w&stp=c0.5000x0.5000f_dst-emg0_p64x64_q75_tt6&ur=a86139&_nc_sid=58080a&oh=00_Af4aCqm-zNYLDbEdIot52Tx-N8_UtgIdeiRia0zDGQ2sfQ&oe=6A1645B5","preview_url":"https://business.facebook.com/ads/api/preview_iframe.php?d=AQIhANUfvTrwLyj4tV6liRZuJU1TrrdjI18rmu6wb7_2ea3LRzZVL6PcTGWFvhcokLLpMzYALoYlvdqVxowjKvC-KRc5ZV9xkUdKdDzB0mdhFoqPQkhO7EeQMF_8hCEx0pQy1-Ykkk42lVkCeFMBO-SYQHJhNqmB5N2ZmpSBXSNdA8IpxFrEwZk6Qv9p-HkHopj6nZFMEl3AIhXCLoU-BIRUBNnrUkWOf92_nfAr40fhp0h7x5mfNmkRCTn9N4lFFP4Vj4lISDQ9X-sL_HfWO9bHSeL-BuCqLml5el6y5P2Ecy8zujrsb1st-6AoA0jrTzYK2jW5wnW4bzcPr-iMIvuf6u32KqTmpOnC3lUSq7RiMTndRGrjo0hv6oL3HfkU2D-Du2aojyadylEn89f-x4E6YXSFYCnULfylssdmcMix_Zt8f1DMbD0nkEy0ikWhrSI&t=AQI0t9cEjGKz2hNfuGY","active":true,"msgs":1,"leads":3,"purchases":3,"add_to_cart":3,"initiate_checkout":13,"lpv":237,"link_clicks":290,"cp_msg":698.19,"cpl":232.73,"cpv":232.73,"spend":698.19,"impressions":18698,"cpm":37.34,"ctr":2.29},{"id":"120244759585190620","name":"VID14","campaign_id":"120244759585200620","campaign_name":"[EVENTO PRESENCIAL MAG XP I.A] - [SÃO PAULO]","adset":"","thumbnail":"https://scontent-lhr6-1.xx.fbcdn.net/v/t15.5256-10/700103193_3526268680869553_4288060750482792899_n.jpg?_nc_cat=109&ccb=1-7&_nc_ohc=N46rWbmbKnIQ7kNvwGN6X4p&_nc_oc=AdrgqyqG-djb6yXA5VFdS7Kk11-m8AvwnBP7j2Geqvo3TMrLQdjXUvPUy0eCYbSR-7I&_nc_zt=23&_nc_ht=scontent-lhr6-1.xx&edm=AOgd6ZUEAAAA&_nc_gid=f2mTQQnWU4Aozu9icrgzMQ&_nc_tpa=Q5bMBQHjxdKAD0TCG55SXksTFjX3wxVEroqOgluW4JBPG7X5wPJ5WSmSGLCkmjHEvBIeAX3jwyPx_z9h7Q&stp=c0.5000x0.5000f_dst-emg0_p64x64_q75_tt6&ur=5fad0e&_nc_sid=58080a&oh=00_Af6ODOI-4BKa3Z8J_hKW1G7d5JWmNv7Y6kuc5_2k_XwIIQ&oe=6A16358C","preview_url":"https://business.facebook.com/ads/api/preview_iframe.php?d=AQJolwemvi_aXi72a8wYq9PlzmmqKKLiZByWMPO9AdLx6MfbbrdftF8DffbhLQ5eJPqXmI4aFFpge6yyKM_Suu8xQo4C6CuMoZcsB8VEswc4fh2_1_zDUAfC9UGXZ2F3qw5At9otWTrTATnyqDgnbfjDKha-xPtmf1RRro5vangu6h6l_HMMsU5VORcJY9QuCqnRwHGpsaTNaBJRyTYTHDDADHp6_yv0cEX7jDLzXJ6DDGisFRRp9UGvlZW3abhXZWJv2EK3soifHfdXd1iuMTLQXF44gzVf7mz1ylAs27LoBVpUC_pseUzYlk06uoilFo5yRhUq2UKkaSxbrWEOX9wQwLzwFzqa7ORZ_CsVYIK504-grK-0_rV9EZsvQVs2_FMyVVuDOUJhGjzKjmVZHctHBc1I-RMhK6vhXMnmn8Dg577LLTkUG1DAbSvS_XZPZaw&t=AQKHuy6MYLzbPkpyzIk","active":true,"msgs":0,"leads":0,"purchases":0,"add_to_cart":0,"initiate_checkout":3,"lpv":92,"link_clicks":173,"cp_msg":0,"cpl":0,"cpv":0,"spend":184.69,"impressions":4098,"cpm":45.07,"ctr":4.29},{"id":"120241197919330620","name":"AD02 —  unico com venda","campaign_id":"120241197873910620","campaign_name":"[CBO META DE CUSTO] - [LIVE 10 EM 7] - [CRIATIVOS SECUNDÁRIOS]","adset":"","thumbnail":"https://external-lhr6-1.xx.fbcdn.net/emg1/v/t13/29333479222778362?url=https%3A%2F%2Fwww.facebook.com%2Fads%2Fimage%2F%3Fd%3DAQIFnrW5-OYCkgvw62je9z0qego4R6BHWbJgqI0QyzkZ2E_CnNdM61nRdo9tcvn8y2h3k6FYWk8ohvR2AcZEoyvZvSpBXdIm7p7kvhS1uU8gT4dgm3_ub-_pvu_lGQUjS9KML4Mr4I__M5J9o-tm1LLq&fb_obo=1&utld=facebook.com&stp=c0.5000x0.5000f_dst-emg0_p64x64_q75_tt6&edm=AOgd6ZUEAAAA&_nc_gid=f2mTQQnWU4Aozu9icrgzMQ&_nc_oc=AdqzXkak6B-a-i4AyMFDO6PxN89TBq0z_NnaXQxxwqPLUOd9ueocVXc4gVgNT3JG0R8&ccb=13-1&oh=06_Q3-_AYaSm8FAXgEIcAkjPg6btIqg_LuVK7Fq6g6vZGXu7gqg&oe=6A124177&_nc_sid=58080a","preview_url":"https://business.facebook.com/ads/api/preview_iframe.php?d=AQKRL4b8ofn1y6N1si_sLgeKZNhdUy24CySWM4Du8XuoVaw3cbVbrH_8rxq6x21BA8I_RvfvGZ4s2nHgzyvMCdjMxECc_GsShCd1ydBkXkB1yd_hTIFfAQcr1V3sfJi8pOODzYRk4SuZ8FZq55Hn9C9kD7-GyPV7Z2RLSicKeraWNvbfVvNhTQ4p7SpgtjyMh6yk5Ohfr23p2pwOcaSfTY8ug2SNSBWvrdmpW3pEmxR0TvcqqGdLdcfYwzlt8Dfy0nL9NML_9Ip0Qbcu2KYF8zohHxb563b39Qs6BSO57UglJ-l9Zcfjt5SlbFYoy_quING4ZLqk8U5bdwLwV2cybxB4Wk-lSPJQqWeQwWi0bg-hQUheYl0RUp67wQ2PaetfQLjswUfTfCCQwc7OJKM_G5QTUbAFC04RZdQw0u4XSRAYmcjh2_GwjcNncsPCZqF48VA&t=AQKgAkghHQ7cH16SaQ8","active":true,"msgs":1,"leads":50,"purchases":11,"add_to_cart":63,"initiate_checkout":35,"lpv":112,"link_clicks":141,"cp_msg":178.25,"cpl":3.56,"cpv":16.2,"spend":178.25,"impressions":3905,"cpm":45.65,"ctr":5.35},{"id":"120244758302410620","name":"vídeo novo","campaign_id":"120244212138750620","campaign_name":"[EVENTO PRESENCIAL MAGXP]  - [REMARKETING]","adset":"","thumbnail":"https://scontent-lhr8-1.xx.fbcdn.net/v/t15.5256-10/702163235_844634118193524_5983110276692691829_n.jpg?_nc_cat=107&ccb=1-7&_nc_ohc=at2QXMdC1tcQ7kNvwFvX6fA&_nc_oc=Adob335lm7L8aDJnqsNoMOE0eQEtiAkOpYhT_oPtYety4OTfQgdN5lhjz_kSVXDIwIo&_nc_zt=23&_nc_ht=scontent-lhr8-1.xx&edm=AOgd6ZUEAAAA&_nc_gid=f2mTQQnWU4Aozu9icrgzMQ&_nc_tpa=Q5bMBQG2DB_kjMnyO2EjMJABkcHhWNRiK3nI-Ckg5JfMuneMw-MR8zKBEWfs8TQbtsCDAsSOXds9CYJO5w&stp=c0.5000x0.5000f_dst-emg0_p64x64_q75_tt6&ur=5fad0e&_nc_sid=58080a&oh=00_Af4gM3HVFxcAlXiN8T4Mfc-zvm-pQ3yBQjnZ0QmrioHfxA&oe=6A162975","preview_url":"https://business.facebook.com/ads/api/preview_iframe.php?d=AQK5ljAKP3Xx2ls4jkFk2C1o6COQNQI8LfW4zR5KuZQNbsm0p_8MoCln2LYIwtXfGgoq2JMcKJKWaNlUBhSG69i9N-DR8XghoXr_nxxHmstz1z7wzJxyf0WKKTc7OXexgtdQLICC3OPLXrnT7umpGH8u2FMVRi7igFkgwhGJPsvOiNurGZLXfhGazI_AmKzVnH4Lh4xM6SI8dO-w4-wcvSvt0pkAVh61v2AcxCazrOq5N-V6ZohrN39pmuNaEiD0SsYrxSW4M0LwuZugolFpdv9KImJfjBZpqC-o-td9Cl3EjvgNoT69RK6MCa-Wtd5ltV5F0y5tdD-ouwJ_kkZW72DU6YL2qkEZrA2NuqXvjOkhl1lPTD_r369kFTog2FTedXvGC-_dDKYVRUv_7m9PPmowoqYuncO1ArM758idwzlysk41uGRc43k5gspuFPaWIzY&t=AQJcz-An4LRXb1AnREY","active":true,"msgs":0,"leads":0,"purchases":2,"add_to_cart":0,"initiate_checkout":8,"lpv":58,"link_clicks":61,"cp_msg":0,"cpl":0,"cpv":70.49,"spend":140.98,"impressions":4530,"cpm":31.12,"ctr":1.94},{"id":"120243549914270620","name":"2","campaign_id":"120243549705150620","campaign_name":"[GESTÃO ADS] - [ABO]  - [VALIDAÇÃO]","adset":"","thumbnail":"https://external-lhr6-1.xx.fbcdn.net/emg1/v/t13/475900884798165916?url=https%3A%2F%2Fwww.facebook.com%2Fads%2Fimage%2F%3Fd%3DAQJwwD4xhOQoFNv0fzWS_41drkVLJpEMnBpGLR5wB8e3HlCKS8O_VIpN9hWXCVIqtKVfyuD2207Ri3NFIUzjXnUyyrMsjN8JDH7VDQhkKAj0sQgLiQP3vPOOPPauGDgQZkPA91t6YkGaAdzb5tjI_Rr_&fb_obo=1&utld=facebook.com&stp=c0.5000x0.5000f_dst-emg0_p64x64_q75_tt6&edm=AOgd6ZUEAAAA&_nc_gid=f2mTQQnWU4Aozu9icrgzMQ&_nc_oc=AdqgKXNjS8Ty9_NRwTxYsJhShmeXHAa8OuVLWPcQ0UTSiXdggFfjWX1gJHirbEI-I6c&ccb=13-1&oh=06_Q3-_ARjrdqY3Tz8L7HyEJNOoUGv3zAgHg-Q7bjywbZnKYcOI&oe=6A123F99&_nc_sid=58080a","preview_url":"https://business.facebook.com/ads/api/preview_iframe.php?d=AQLgAiS8dzxOmq6l3Jio3xjieFfZOpCDeFjG_b4C_wIba6BqIe4mdgk-rzSwb9eK1r6vpOXiZxAjfelSMyVCExiPgFz3YPsjBm2SNIjI711C3bvzUaOjE-NT3rTTNW4YmNHKurOvP7vamfe0HEIi48tBhoOhcJ1uyZSWj2RSFG3ueTqObvGOvxnqQV_MxCmheYIrfqDS1zvz1DWcCj1yNM9twkhult0BPgAzSmkV2z76riJUiH6hnOJ1yGEesyIXIeDsZvM5f_cIvO7_ft4IvDxY4MGf8zOY4j7be6ypBOqrbPqEfn4Hp5QMuZSJVorfBdF9OkJATiN2QUQtwng45Cn8ogMD3Ttl28mAGprJSvrYNNfGiQ55uWp8hAz_2f1iTX88v_43ZPs4pLqPFOudKWayf1m1Uj2q2s4_30O7l-4YTSU0Fi-bCcKklGNZdMhtdB8&t=AQKtOUFJg8CdBdJRMTw","active":true,"msgs":0,"leads":14,"purchases":1,"add_to_cart":14,"initiate_checkout":0,"lpv":75,"link_clicks":82,"cp_msg":0,"cpl":8.13,"cpv":113.84,"spend":113.84,"impressions":2363,"cpm":48.18,"ctr":4.19},{"id":"120243788057740620","name":"vid01","campaign_id":"120243549705150620","campaign_name":"[GESTÃO ADS] - [ABO]  - [VALIDAÇÃO]","adset":"","thumbnail":"https://scontent-lhr6-1.xx.fbcdn.net/v/t15.5256-10/689848270_1691632318522229_941592015396329464_n.jpg?_nc_cat=110&ccb=1-7&_nc_ohc=BeSSbs0XkSoQ7kNvwECxFIS&_nc_oc=AdqEnIuKKjvw6cQD7AHAlf8Od3npw3v9bjkg2PA4pYVJkxA7RJ9CoA_n68biKh-2KoE&_nc_zt=23&_nc_ht=scontent-lhr6-1.xx&edm=AOgd6ZUEAAAA&_nc_gid=f2mTQQnWU4Aozu9icrgzMQ&_nc_tpa=Q5bMBQG1nq3caJihtfEwjnFPPriAITBYMBE_0Ybr5mUM6QWhCq02e7-wvbRCc0fpuPwV00515nESc9Te_A&stp=c0.5000x0.5000f_dst-emg0_p64x64_q75_tt6&ur=5fad0e&_nc_sid=58080a&oh=00_Af5or4miAVFdHf8nwVGTxD7GYBY3iCeaFxQ35xVo70Vn9A&oe=6A1641D2","preview_url":"https://business.facebook.com/ads/api/preview_iframe.php?d=AQIaBJtjomlwG_uf7gFH8WQefpnJq_lTCJ1NhxhWTcX5zfM-CnE5wTECuv6FU4z5Qk98b4nLfyiEeinN0HeekPiNJmJN2tdSrfVIIUL-jcKMkH19K4fvo4ARgtySbUXze52ZiFL_FWgX1Ue17yYUZEAG2AIts_1sKZjSsHrJKmAGS4K0LhqPM9TYPtqrlXIK2ZaIdo82T8xwTTusudlUQ9kc21SNYuP2I2naua1tjac7cgoVfNTJm8uOtAfz0iFjKXjnQGE6OGU0inFfm2pxykXhfqoo0Pm6gRxePXDf1y4wCCxf-Iq2xg-pY0boQ8Spvndw9I_Submo_O6snCL0C-EA53m1PjmJCB1T2EF-OnNt09z3P3hfoW27trNYIr7JDy2jMlLrXniOtATNtVrwzYB4MFHOb4SoCjLkypPyXKpTK87qnUTcmeXHb1k9rkduiUA&t=AQIw93wVpZxsIB1uR3g","active":true,"msgs":0,"leads":2,"purchases":0,"add_to_cart":3,"initiate_checkout":0,"lpv":36,"link_clicks":50,"cp_msg":0,"cpl":51.23,"cpv":0,"spend":102.46,"impressions":1527,"cpm":67.1,"ctr":4.85},{"id":"120243788089230620","name":"vid02","campaign_id":"120243549705150620","campaign_name":"[GESTÃO ADS] - [ABO]  - [VALIDAÇÃO]","adset":"","thumbnail":"https://scontent-lhr8-1.xx.fbcdn.net/v/t15.5256-10/691544947_1947323996148848_3652476147167007732_n.jpg?_nc_cat=111&ccb=1-7&_nc_ohc=Jf-3K-c_w4EQ7kNvwGjEFxJ&_nc_oc=AdrjY4-ofYI6BJeDwMc0ERhHQioxZ3GT2dvkQALV_a4xwSIyKHM5x4UMMgHaPpm_dXI&_nc_zt=23&_nc_ht=scontent-lhr8-1.xx&edm=AOgd6ZUEAAAA&_nc_gid=f2mTQQnWU4Aozu9icrgzMQ&_nc_tpa=Q5bMBQFgnhcyFhtX6ix_lTimZIBR8GmMG8MRRpUWir4vTlqFA7TYB1H4MF0JjhzGtgQVWsg_h7q4D9ZFrw&stp=c0.5000x0.5000f_dst-emg0_p64x64_q75_tt6&ur=5fad0e&_nc_sid=58080a&oh=00_Af6KSvyEayrU9qMIsUnSbIdcR4uzDiiJTaybaMIMjul9gw&oe=6A16201F","preview_url":"https://business.facebook.com/ads/api/preview_iframe.php?d=AQKu9OiiM6km2b78Q1NX5JJ9aPtAkerGfzxjSfwr70XjJTzolrdkMO5-Z9P8-PoKqmVzDhPAeKoVMUI8xEEnDoDJIU73H6_KbXUlgoFVBLiJRYrKanNABb2BSbNmYbq_YaRgKFpugYlfcsi_ilRvcyw5bfgvpaTTqwPHvY5tPCjt4byYMYVLFZWJLAYteK2n59ZBMgVEfB0_Ojhr28Z5UKrYvx-wI56i8sTQlnRP5SvV0TxmGPz4y1hfxsvQecmtuTV8JsvdO4AvAWZKDfxZ4OEyB5wawAs5PcUU9MgfpYpKOiRTXndMaqBfel20fXBD7X2YJikhC2oOsv_pPTSnBEHWkix_swnJ72cd9fmqg70tkQqCJ2VWeX5rjHLSFVoTSlWT2rghTyWYjxJ_21xj5r35w4-pf9gcb248cI2oQOnBrnNaOU-WWEHRQ6qhtOkTEMk&t=AQKT8wfbPZHWJeIES0A","active":true,"msgs":0,"leads":2,"purchases":0,"add_to_cart":1,"initiate_checkout":0,"lpv":39,"link_clicks":53,"cp_msg":0,"cpl":43.81,"cpv":0,"spend":87.62,"impressions":1480,"cpm":59.2,"ctr":4.26},{"id":"120241882122750620","name":"CRIATIVO 6","campaign_id":"120241881649680620","campaign_name":"[CBO] - [POLOS SJRP]","adset":"","thumbnail":"https://scontent-lhr6-2.xx.fbcdn.net/v/t15.5256-10/663353453_1616431912809967_8865566238118576285_n.jpg?_nc_cat=104&ccb=1-7&_nc_ohc=jgNUQxDuGFAQ7kNvwHc7xZd&_nc_oc=AdpihVSXPm658FJ-iKpZ04m0U9jRxsiK7MywqGlfhwBmc9QYRYkidMMhQWqIcOuh2lc&_nc_zt=23&_nc_ht=scontent-lhr6-2.xx&edm=AOgd6ZUEAAAA&_nc_gid=f2mTQQnWU4Aozu9icrgzMQ&_nc_tpa=Q5bMBQEfgl-wE_XgexfnWN45xV5H03yKzx11Qwdw9IukzwXDQPG-tL7ldm96_FiHVyEhUUixl7oto3BYoA&stp=c0.5000x0.5000f_dst-emg0_p64x64_q75_tt6&ur=5fad0e&_nc_sid=58080a&oh=00_Af5NlbRllif3HrrlHUZ01RRjuRavTp19WbiCuNEV577paw&oe=6A163FFC","preview_url":"https://business.facebook.com/ads/api/preview_iframe.php?d=AQKnaMu6UkRp8yeK2vy8q5vttrlGNmF0zstVEpkZqQFQXdC7cP-r_d3hptamiCDzjymszeqYUftSazaapB6zqXoIkijyQiZBqnCv3B1m9HECNgjxXTw0Un1K20PTeMfezExRM3d3EiTahc2Msd2z8ckdcOgDg_0Nm1nE_9O_nDP7qqLcK8MuRrtiQCmP90tEpR93VYC98AGrbXTLGXFrVen0ipB3GLw2-IrRUHA3zSRxGLG7Z4ZfcrGAMJRGUXcSLmOpHLbv56eotMB6mDjj7tEuRndNk5_ZclOC12mB9xZM-5a1pTofEFfkizFsTTnBRzOdH6GvZubbVSq07BhlcWvF4yg_5HVci1rSPa6qI6WmN8_S-MLEhNDVYjy6piqouMyEVZEbEzzNJSw2Nuw210B90_t59LK80gbO2UYQFC83wwwdkPJypk0M_NM5zKKIbFQ&t=AQIyl5QrpZ3dbzGucdw","active":true,"msgs":0,"leads":2,"purchases":0,"add_to_cart":0,"initiate_checkout":0,"lpv":0,"link_clicks":19,"cp_msg":0,"cpl":35.37,"cpv":0,"spend":70.73,"impressions":2037,"cpm":34.72,"ctr":1.62},{"id":"120238547411620620","name":"CRIATIVO 2","campaign_id":"120238546111100620","campaign_name":"[POLOS ARAPONGAS] - [16/01]","adset":"","thumbnail":"https://scontent-lhr8-2.xx.fbcdn.net/v/t15.5256-10/616380693_889458796910564_673795906714405048_n.jpg?_nc_cat=106&ccb=1-7&_nc_ohc=O5_Fe0vi4hYQ7kNvwEBqVCb&_nc_oc=AdrFxejxPPzKXN37LutxaIuHMjXvaheQB7J-EspTM7edJhGssuW7a-0nxAnS8N3WL9o&_nc_zt=23&_nc_ht=scontent-lhr8-2.xx&edm=AOgd6ZUEAAAA&_nc_gid=f2mTQQnWU4Aozu9icrgzMQ&_nc_tpa=Q5bMBQEuc3J8eyp_Ti9fBYROlSzjd0-UvlgJJtlliR8ugZgOv5lOkRAohklB7T6B7lyGo6tG0bNAiz7aVQ&stp=c0.5000x0.5000f_dst-emg0_p64x64_q75_tt6&ur=5fad0e&_nc_sid=58080a&oh=00_Af4R3myDP6xB6r2rc5j_nq_tODdKEuoYy84sEK72u6-GFQ&oe=6A16447E","preview_url":"https://business.facebook.com/ads/api/preview_iframe.php?d=AQLTCStjK_kUubuuAZ4uEVLN9I3l5J68Et8jSlElfuXvAUA4fHJrPKNKOhkQ2nSL88CNty_tM3vQY108iM-HXhM_UblsMUnBnpUxBm8Koy3IsqEZa16MNOWtvQrAJENqSPHxzY_rB95jWStWFbQCLsaywaaembBhjZj9uhi8phKRhk6nVNXKG7r9VEPuPL703CIP3cWSnzPsYf3SIzocNcYkKH6mX8i5__e9nPqzFHJY4tliHhd6WGEATZGMXEe_gzJ-97CTGBr_pnDylmU2374cm6JMekerRBE0MOwdyM_sFgLIoUjsAgrVbH-cQIBvgmcJ3IGGkW9h8YMzOWp77PVUbh0b840l7M5RLLeub-WsaYXYrEvD-JGJygQ5a2DIClDodH2FeObc_S18TrP3oN89mmc36jEH-qlgSEMm_kzkuFfNWYE967LsRhuSQXL-8cA&t=AQJ9y6X-dWxE6HN3UFE","active":true,"msgs":0,"leads":3,"purchases":0,"add_to_cart":0,"initiate_checkout":0,"lpv":0,"link_clicks":9,"cp_msg":0,"cpl":21.22,"cpv":0,"spend":63.65,"impressions":2964,"cpm":21.47,"ctr":0.61},{"id":"120244759742420620","name":"img","campaign_id":"120244759585200620","campaign_name":"[EVENTO PRESENCIAL MAG XP I.A] - [SÃO PAULO]","adset":"","thumbnail":"https://external-lhr6-1.xx.fbcdn.net/emg1/v/t13/17788208537051258731?url=https%3A%2F%2Fwww.facebook.com%2Fads%2Fimage%2F%3Fd%3DAQLxTiJZteVCbguL1f1vs3aFkFR5M5mvhcqcqA8JVgKsgcZCmk4D1qDMuyXIVZojq5iYyDOCQJ0NUf1HUVMvGMpow2RokhsQZZbw8-j_uP5zJhoEm7__wT1ABOuZLdlxtJ70XyM0tmPSnU0nkI8-OZg5&fb_obo=1&utld=facebook.com&stp=c0.5000x0.5000f_dst-emg0_p64x64_q75_tt6&edm=AOgd6ZUEAAAA&_nc_gid=f2mTQQnWU4Aozu9icrgzMQ&_nc_oc=AdpqB8v5wuLN7HiO9aRlQ8_5tzI6NibY1AtTHPVgUECRqmWT-jAwNpkIudubd71Pidc&ccb=13-1&oh=06_Q3-_AYlxxOHdJBjup1NVeTmXz0HoRBtdHY8Y2Wwr9DkU7eMy&oe=6A124C7D&_nc_sid=58080a","preview_url":"https://business.facebook.com/ads/api/preview_iframe.php?d=AQLCKVaxPnChR5LtY-CEcWHs2oRL_Ic48NnvT8dDFTHpuMNOYarDuL1gW4pc_A4PAQNZBGl-V98QA74gjYQA8-ZpnhEcsSDJWGjoAegUARG0UUBKph91MSXBOaEs_RTppSHVCjB6Fu_MFUamPjh6LKXUApT7JSdiwWD5KK1g5clDdkOchFxLfvNqUOD3FJghUy_ryuvh7gMjTyrSwsy2IBJnT-zXQruW3pgRlYy7dU9r9wUW-dlHmVW5vRe16Rubnw1tH2f9_0JaIWfvOMoFBYTdj4dLKrSMr2bQS8QFTfWUUN-46I3-x4OAjOmJkFYkzeY5X9gCDkRKQVwhskdeFGKLtB1LGk39yiJyc_nHpBI6u-D9d0ejWfTjrR8Mmq_sLege6SZ3mj2JrUdZiWmDp3BVavXXARBi8zD99TMpCjwAeTImW9SH_pOe5LgfPzeVq4Y&t=AQJazLxeV0aZTzIs-3o","active":true,"msgs":0,"leads":1,"purchases":1,"add_to_cart":1,"initiate_checkout":3,"lpv":15,"link_clicks":23,"cp_msg":0,"cpl":61.79,"cpv":61.79,"spend":61.79,"impressions":1003,"cpm":61.61,"ctr":2.19},{"id":"120244212335760620","name":"3_VD - pag nova","campaign_id":"120244212138750620","campaign_name":"[EVENTO PRESENCIAL MAGXP]  - [REMARKETING]","adset":"","thumbnail":"https://scontent-lhr8-2.xx.fbcdn.net/v/t15.5256-10/691899506_1282814560624784_5572589473674382964_n.jpg?_nc_cat=106&ccb=1-7&_nc_ohc=kAXWVLnxd2YQ7kNvwHzIZCF&_nc_oc=AdonZ9Ex-eUB_HwnQTrnPR_anPMWYfhKEDDQ-mrb6rgyHxmOtyKjllNvlHmFlpL9X7I&_nc_zt=23&_nc_ht=scontent-lhr8-2.xx&edm=AOgd6ZUEAAAA&_nc_gid=f2mTQQnWU4Aozu9icrgzMQ&_nc_tpa=Q5bMBQEeRRJBx7O75pKlo8gn53Gh9nDi0tKe_DvGavKAi_NciRO6WKedhGqvwAjGCramzSPog7t5gsy-Cw&stp=c0.5000x0.5000f_dst-emg0_p64x64_q75_tt6&ur=5fad0e&_nc_sid=58080a&oh=00_Af5rYFu9EAb48cIKyxBCcVT43x4tqfmsTBhwCDvhBLv_kw&oe=6A16313B","preview_url":"https://business.facebook.com/ads/api/preview_iframe.php?d=AQLv4eevlOI6Ay41ZP2r_cOGDKXMLGbwa8gnydplCbg_N6Imyyhcr3n1TulBQGXoGKMsG-1teWTkda2821UwlDndbOwVkq6lJZPVWCW6kmZR0WyNLj4YbOxIYaQCiL_WPfPIRF7ATEHrJ-ezT7FhuTKJBMcsoNAtkfrUsUmiwZ4BvaphwzOwv5rUJxpVuSOWIW-6H_-BkPaWoeJQMXYIIs7bPAqDjxQKlYOc5O18CJvnRtlV0DBVwb3jj7sZoRDCKsyXPkP6Mu2q2lweRsSBKgYEEkoDg1mMeRR2HLfvz1we7IKyMXWmxb6dwsPOEbYMj27hM1WIqdS6QImzpBdSVMwITiuiB-iHlYAl5Uk-eW1vaSaLpmTSG8sKgXFV_5LLtBHeR0FRBvVCLbuq2Q7oF7io3qpgZSgomZt5hbSLiJUTk_x_jhhiXSsJVz78J7DhzaQ&t=AQJNrOjD1Yk7ra9nbwY","active":true,"msgs":0,"leads":1,"purchases":0,"add_to_cart":0,"initiate_checkout":6,"lpv":9,"link_clicks":12,"cp_msg":0,"cpl":48.14,"cpv":0,"spend":48.14,"impressions":1216,"cpm":39.59,"ctr":1.64},{"id":"120244683638240620","name":"imgWPP","campaign_id":"120244212138750620","campaign_name":"[EVENTO PRESENCIAL MAGXP]  - [REMARKETING]","adset":"","thumbnail":"https://external-lhr6-1.xx.fbcdn.net/emg1/v/t13/6612471901489238282?url=https%3A%2F%2Fwww.facebook.com%2Fads%2Fimage%2F%3Fd%3DAQIdsAG5RDZ51bTute6-1G5lhBD9n9aJM9z63tlZ6M-_DaBB3je1B0xg8rnGvjOMmoVb0IEd9L8Nf-vq8njY3Q-py_D7ircQ0FmDYv_7pwBTlaa3x8o3HR-NhI2b5BDJMCT_BBJ5XClu7ekE1h9bIKxR&fb_obo=1&utld=facebook.com&stp=c0.5000x0.5000f_dst-emg0_p64x64_q75_tt6&edm=AOgd6ZUEAAAA&_nc_gid=f2mTQQnWU4Aozu9icrgzMQ&_nc_oc=AdrjHczUmm7RFkSb5rXnFsUEDIW6QijQJrKE1O7g-yPa8P6ZzLrbDTxnURKREDRoc64&ccb=13-1&oh=06_Q3-_ASxVLOHMVN_eRsHG0XQeWh5IOXGtXR0HBsm1p1OO29tv&oe=6A1248D0&_nc_sid=58080a","preview_url":"https://business.facebook.com/ads/api/preview_iframe.php?d=AQJoWfAhyvbHtQk8crlgiZ13f-zevuElaP4cxh5z2avWmdzzNwiazpOSA4pmaPnH3f-Q4B475BV4FR8hODeePEXKXi9qblB8SFQZcHrSy2GFDGQ83L8834ouEIG6E-qdSiRl9cRWRbNDN7B74D3BmpHT9QThrEZowDYDUo9JR5Jmb23rV_Q6-1oij0IxS8WN5muof8OBPix--5DxOUtRHX8GuB6RV3WHs3OETjpr8NWKp7wFW0HipfYkGS6xys_KSeSnWPHOkznLjnepd7M1WgTb_n79Fnx_YfwvClwKVsuYx21GR-rCBRSgWTH9kKFhEBi4STKwlgz1JnofffI3h50oB8W0KseyMxhAS5rx3z9mzEeHnNTgfwpPX8fvZbQnyrsoJk8W7P83wHp3VmHsTVYhW7byT-seKEF9jsYlSh1wsd0nZlJS37W7QhsmsX7bACI&t=AQLtKEr6Q22AojHrNLg","active":true,"msgs":0,"leads":0,"purchases":3,"add_to_cart":0,"initiate_checkout":4,"lpv":16,"link_clicks":18,"cp_msg":0,"cpl":0,"cpv":15.29,"spend":45.86,"impressions":465,"cpm":98.62,"ctr":5.38},{"id":"120244757587280620","name":"RMKT_IMG","campaign_id":"120244212138750620","campaign_name":"[EVENTO PRESENCIAL MAGXP]  - [REMARKETING]","adset":"","thumbnail":"https://external-lhr6-1.xx.fbcdn.net/emg1/v/t13/4304592186188193668?url=https%3A%2F%2Fwww.facebook.com%2Fads%2Fimage%2F%3Fd%3DAQLLgXQrWPshp-EQHhm0NJANrzKSf9_bgrfmWpFT5H2MP5Ku5aTpZXcR8upIEd8NY5pL1L-LSHPDImkmQTaSCIwsVB_pJgkhBJoP-hVM3UZjyNW4eMvNkQO6iQmtMoSFtqgiIquQxci1Vc1ZzpFGGLnx&fb_obo=1&utld=facebook.com&stp=c0.5000x0.5000f_dst-emg0_p64x64_q75_tt6&edm=AOgd6ZUEAAAA&_nc_gid=f2mTQQnWU4Aozu9icrgzMQ&_nc_oc=Adql-3OrUEVVb6uagKwK_nXVMcsqIiqX5cGhWAx8Vst27nPmOZOsf7c5fbFbl3cASno&ccb=13-1&oh=06_Q3-_AVRrv1U4BX27Kb06MrBn3NFUTmFclh57aaJLaDnxMAB0&oe=6A124324&_nc_sid=58080a","preview_url":"https://business.facebook.com/ads/api/preview_iframe.php?d=AQJq_EKeHrBjX3AAozzQh_OxIHfMH0M_cfwbXeZiYTlCFdvAmdwbvDQ0921hBgmVQ_8GN9XgDKKXD8Lrfe5WLU8BYzWUjT-2pA8Ts3oYG1nST7yLSMF7242TAZ2lJInqgcm4FSNUr9tOlhtcHj9IUAd7VpW9WsTDsjXMTNOd_aGBDv6IHKcMmmxmROvaCtvDB5ZHAeLHt6-mAyeUq21-lsJUj8P4qtvnZANGqKz3vpOajsLjW73mrWiOscLSV5XT2P3i7Ke57XTzLum8fuM5_86vKNVpN9hDvvW1Uea4YROWGJaR5JE_piCc5DxK1ib-bbjS-Bd7RlCMKkSZClam4Zazs65OactZVEalkOR7LBaxcQkvg9hq6NSrs3nAJEIPfg8RNfwJVZFe33KNYDTeWhBcbDyfTdIwfYafpHJluSsu-6le_Ptq8qOkSppc0PJaYN8&t=AQJ-u45Hlr3WzOYcVM8","active":true,"msgs":0,"leads":0,"purchases":0,"add_to_cart":0,"initiate_checkout":1,"lpv":5,"link_clicks":5,"cp_msg":0,"cpl":0,"cpv":0,"spend":35.26,"impressions":736,"cpm":47.91,"ctr":1.63},{"id":"120241882122770620","name":"CRIATIVO 4","campaign_id":"120241881649680620","campaign_name":"[CBO] - [POLOS SJRP]","adset":"","thumbnail":"https://scontent-lhr6-2.xx.fbcdn.net/v/t15.5256-10/663353453_1616431912809967_8865566238118576285_n.jpg?_nc_cat=104&ccb=1-7&_nc_ohc=jgNUQxDuGFAQ7kNvwHc7xZd&_nc_oc=AdpihVSXPm658FJ-iKpZ04m0U9jRxsiK7MywqGlfhwBmc9QYRYkidMMhQWqIcOuh2lc&_nc_zt=23&_nc_ht=scontent-lhr6-2.xx&edm=AOgd6ZUEAAAA&_nc_gid=f2mTQQnWU4Aozu9icrgzMQ&_nc_tpa=Q5bMBQGaqkWjoz9prhvZNx20sZ1DkouryiLL_Ho-eQzo7AOiyMCsHgcuQZbYEWd3U5zTjOWWbRWaS96bmQ&stp=c0.5000x0.5000f_dst-emg0_p64x64_q75_tt6&ur=5fad0e&_nc_sid=58080a&oh=00_Af6HVzAN1kE7qOhxNhOYT6iayNOVIskhVbIhaxtNFB5kwA&oe=6A163FFC","preview_url":"https://business.facebook.com/ads/api/preview_iframe.php?d=AQKlqneV0F81h7PXHqKdDFNoej60FDA1H1A6fG9DssJT30y2QlW8k-kJmt6WpN3x0L_ffa7PYB30RBwGwkShFdsoXc5JBNgR5CIFsjBqEyX-DFWqgnKjpUGb9uxd5H_yqfwLd2MhOwJUWAbBMYESdSwso-FnHILHURATcPU040v-NNRUjXIrHGXJLKyKvxDQVAE9KsuDhBGzR7C_q-S5hDEelrt0Cq6R6l1z6xl2vk1X3cK6z01uaA9Y2Zzfe8MWE7xuVx7I5lLbaoMQIh4mcqH3fjis-VAA61pVAZXBunBPfhbD4jtkk4t_ym3vXINseZj2p7_7bXwDomTbD5VzxjKR-wFdWXRmNS63bSuDrTYX0983p55PrYgzWFvXAxuQXWDtmQsR82cJB-fvFsQ2be1i8W7w7_5LW-Isor-rjmfTb2k5YFPblsR9MsU-yTiGcvs&t=AQLXaOcqaRtYtv8_d4g","active":true,"msgs":0,"leads":1,"purchases":0,"add_to_cart":0,"initiate_checkout":0,"lpv":0,"link_clicks":9,"cp_msg":0,"cpl":35.13,"cpv":0,"spend":35.13,"impressions":1012,"cpm":34.71,"ctr":1.19},{"id":"120242286234110620","name":"REMARKETING1","campaign_id":"120241197873910620","campaign_name":"[CBO META DE CUSTO] - [LIVE 10 EM 7] - [CRIATIVOS SECUNDÁRIOS]","adset":"","thumbnail":"https://scontent-lhr6-1.xx.fbcdn.net/v/t15.5256-10/646822081_864999696613886_8272251872686959386_n.jpg?_nc_cat=109&ccb=1-7&_nc_ohc=2E1MLiR3LHkQ7kNvwEhOAwT&_nc_oc=Ado6dFVwJF-sXQh3aQZH2HGIqYBzL7JG-xH7MIFJd8gcOOU6FzDu8llWG7XOdh8VZAc&_nc_zt=23&_nc_ht=scontent-lhr6-1.xx&edm=AOgd6ZUEAAAA&_nc_gid=f2mTQQnWU4Aozu9icrgzMQ&_nc_tpa=Q5bMBQGukc1J0KvrKTVR8QAmiDthZEzWJptR3wVf7VjX5xoBPW7aTNCkjGwdClGyVZeWqM45e16PGm_Duw&stp=c0.5000x0.5000f_dst-emg0_p64x64_q75_tt6&ur=5fad0e&_nc_sid=58080a&oh=00_Af7pahghMUF34aMO7VbqxA20iEg8kwPJyTDFDZdxJLMM7g&oe=6A162145","preview_url":"https://business.facebook.com/ads/api/preview_iframe.php?d=AQL0QR21hi0NhsDvi1wrB2ip3eEriJzEifVtyt1vuhFz6htq0Qw_hnoZxLL8tetWYYCjvQTofSzSEOhjOR8ihTgTiuLVPYyoVEe3wHe4g-LZxQ67GOy9H7mKGCm66oVd1Li6hnmzSJAReY89BjNJvpD01-vNLz79RHIamVDdZBrBQNbx122vToxR4u9ZixgK-Bwcw2ZmVZQrPfnNHxxuhDaSJ-hFNaFXJmRuE12ORQUShy3JNVtsNyvoBbdrY63LudQ8wbMbzWl5MsQnm2qmwL9eb7vcjTPiPRM9wr29JHwtqHwFDw45RQWei8EDryJN--Gus8tepx9caIYHv13DXXN7zIIFD6iNrKS6Kd42anVZN7BnytgffH5_G208I_IXDLw3NIX60v6c2lMDnznKhWR0Md66LgQ4FLAOf3YPwdlmLU8Gkki3EMuIVryR-JgKZ4I&t=AQKRP2V0K7QRnNJUX4Q","active":true,"msgs":0,"leads":4,"purchases":1,"add_to_cart":6,"initiate_checkout":4,"lpv":8,"link_clicks":11,"cp_msg":0,"cpl":6.72,"cpv":26.87,"spend":26.87,"impressions":394,"cpm":68.2,"ctr":5.08},{"id":"120239522595710620","name":"CRIATIVO V6 - esse","campaign_id":"120239522595750620","campaign_name":"[Bento Gonçalves + SERRA G CBO] - [VALIDAÇAO CRIATIVO]","adset":"","thumbnail":"https://scontent-lhr6-1.xx.fbcdn.net/v/t15.5256-10/623000828_796411000138639_7975145142809139061_n.jpg?_nc_cat=102&ccb=1-7&_nc_ohc=VCthZWMoVDQQ7kNvwFp_rZE&_nc_oc=AdrVLo6x0St9SsmJk046kwE6WBNI5O65tzOmRnVBK1nrb68yWj9pesSDkGzlGkscIoM&_nc_zt=23&_nc_ht=scontent-lhr6-1.xx&edm=AOgd6ZUEAAAA&_nc_gid=f2mTQQnWU4Aozu9icrgzMQ&_nc_tpa=Q5bMBQHCFftTAkUUF1IwAyccwK3A9zTNIFiODAYjtN7LbJxUG4yXkRR-A_0mJ6sUTR7zC7xf5TuQsnqUuQ&stp=c0.5000x0.5000f_dst-emg0_p64x64_q75_tt6&ur=5fad0e&_nc_sid=58080a&oh=00_Af6mugMfMVdFXiCXDlt5t4ONH05N-wNL9qZ4g9E64Xv5Hg&oe=6A1627C4","preview_url":"https://business.facebook.com/ads/api/preview_iframe.php?d=AQIHwmlJMRTtMUuaq5isssYJ0SIR75kaEexOn4uqNAQz9_iNErhtUIA_qyroR0myU_5IWR2m1Y0KDb4qIyOoXqC29esu2f37iZ-IUYrP8uWt76AVb8mEcCbGpSzHeEcjqWG0L_K_XZGPgv7BjiYk-yUw2nw_RnrJmgFN0QIMHezcJHyOrmWV9lsq8uqe_XLhhtzFHhGcGQINpV8vNZn8XJwHRbe4WMN4KKPmIBC2-WR3mKr3ZZxXmEbPZrTmT59SqwzXzUZTu0ZKEl73nOcv6XVe7z56C5eiLkK99wIi7v8BGw02hsWJ6Ud_L8GcLCBBr_5_yTy5jZVVdTnoHi35nhjlylefxQjHR5ka_KzGJDzrTq5qP0S6vkeQBWU9fKmcP6_o6zRJFHK7QsS14oR9Hsr8ngv2IpeafJOXAlctfj84p6fOs57DtwHGX3GkAPNrnRY&t=AQIimBRPv331ujxwEDM","active":true,"msgs":0,"leads":0,"purchases":0,"add_to_cart":0,"initiate_checkout":0,"lpv":0,"link_clicks":12,"cp_msg":0,"cpl":0,"cpv":0,"spend":21.71,"impressions":999,"cpm":21.73,"ctr":1.7},{"id":"120239522614720620","name":"V4 — esse","campaign_id":"120239522595750620","campaign_name":"[Bento Gonçalves + SERRA G CBO] - [VALIDAÇAO CRIATIVO]","adset":"","thumbnail":"https://scontent-lhr8-1.xx.fbcdn.net/v/t15.5256-10/627163014_1220751519654537_7183432736883192713_n.jpg?_nc_cat=111&ccb=1-7&_nc_ohc=DtFo9mn0RD4Q7kNvwFSvFjt&_nc_oc=AdogXzFpmT8lZY-04RY6fXOUqmdjoB_-6_qlRYIngADePbHEKBXgvR8hpAmAJ_255Nw&_nc_zt=23&_nc_ht=scontent-lhr8-1.xx&edm=AOgd6ZUEAAAA&_nc_gid=f2mTQQnWU4Aozu9icrgzMQ&_nc_tpa=Q5bMBQGONpuBkZNBVo6OGIKDUblY1dLx7tqKo4iBbpTH8WIRWDnlnHOCGp48gvO1JqZNQ92pJZrqVFSuNg&stp=c0.5000x0.5000f_dst-emg0_p64x64_q75_tt6&ur=5fad0e&_nc_sid=58080a&oh=00_Af6nr_RvOlA7w_ux2axsPtPgvD-uKttJrWZLids0Yt9kqQ&oe=6A163DFE","preview_url":"https://business.facebook.com/ads/api/preview_iframe.php?d=AQLeNd3AyzUTHOXw7QqkO8OHIvl8Ao-nmugWlvCS0RAEwBFyYR6WbTs5ppA-KqUMhnZVkE5c4KAb1lOK5D2VVtUmtARhhHFKj41z4xvYYYqiS3o2HzrJQzORVLYv8i6F074dYij2bCETsT_X2vuKXzUw0r9-gAjc_uzbAu_haPY4chJS9dgVJ-nmdI5WeCu1gCyr-ujT2KsUyiE7km0dEMJvaNJeluPgF5k59i1LfRgy53gJfuCmGgmtlmam89xPKZxz3HE5pLgNPF_lknIN1HdlmkfmaJbCQCVfN4n58Q7uFeqBeLeSo-0aMBjIuEW4J_jOKA2xfiaoWYEj0hqg6FEBhlfzFiuin5AKsmEyHNvarlb7mpEDF-rc-NukyRGU4Q0Jbh2Xp54goKOfJ2mzYCNDLaru10vVXeRTovPC1ZSS49TbcHZK4tSNFZObNNmekCQ&t=AQKTxQlUZz9pkV5azS8","active":true,"msgs":0,"leads":0,"purchases":0,"add_to_cart":0,"initiate_checkout":0,"lpv":0,"link_clicks":3,"cp_msg":0,"cpl":0,"cpv":0,"spend":14.27,"impressions":712,"cpm":20.04,"ctr":0.56},{"id":"120242102462720620","name":"CRIATIVO 5","campaign_id":"120242102289220620","campaign_name":"[JOINVILLE S DO SUL + S BENTO DO SUL] - [VALIDAÇAO CRIATIVO]","adset":"","thumbnail":"https://scontent-lhr6-2.xx.fbcdn.net/v/t15.5256-10/659649700_1494654958909651_8721257722787679837_n.jpg?_nc_cat=104&ccb=1-7&_nc_ohc=S9VrkqwKz1AQ7kNvwEzsvlM&_nc_oc=AdqxIzWWGeDaQ2HHDripES9Rd7ELZPaoUUFUVCLymHfVtkdhf2ACwBhoE7NT8RUEDgQ&_nc_zt=23&_nc_ht=scontent-lhr6-2.xx&edm=AOgd6ZUEAAAA&_nc_gid=f2mTQQnWU4Aozu9icrgzMQ&_nc_tpa=Q5bMBQGWBnYuIzQwk5VqBpWm24nrS-3hlHhn4FXpBJyQ4VN2quG8trWiFwXfG0RAl1q1qX9j3ncTR2VTRw&stp=c0.5000x0.5000f_dst-emg0_p64x64_q75_tt6&ur=5fad0e&_nc_sid=58080a&oh=00_Af61D6LEYhEs__-fn6k0y29sWDfCIDtlLxkUlKpRmnZR5Q&oe=6A163237","preview_url":"https://business.facebook.com/ads/api/preview_iframe.php?d=AQLDn9MmPO5kNOpwz0jhvPeaotFKfSGatQqK6SSLs_B0JvqZ9OqcsTcjPVEMtzKNJKyXQ4bs6JecrotCAjhMyov16YfNUuXPQF0YvKc7cbU2Uq7DXtmtlMjTl9oYuQV_DqjAA3U6FKyytquSzNQg9u6s29O5WAw_ibN8Wf_jiUMsDpLFh0Le9_DSSb8JmvGPTCBdazrTOIZGFvyNBsFgpwt9B3p5UaA7ND94q_wtOaG8Uc7-ruepaqTxJJ0uHyWGgjchQF4OpoP_aVKXMOjszEwl3Ow052ceja0fxDGyguxVz0WZAXSAyHZPEess1S0eAwJR55b4VThJj2kEJZMZoK0ZQ9msCOtuym4aCGfH_E2Tw0HXi2nvICp1ud1-uLsVzIiolIICvcytJPIDA0u9O571aL-i7thgIvmfv9C7vQMn25n2aUsH4x3Up5fD6PiibJI&t=AQJXhO44XBiE4fWlTWs","active":true,"msgs":0,"leads":0,"purchases":0,"add_to_cart":0,"initiate_checkout":0,"lpv":0,"link_clicks":4,"cp_msg":0,"cpl":0,"cpv":0,"spend":7.43,"impressions":277,"cpm":26.82,"ctr":2.89},{"id":"120242102462710620","name":"CRIATIVO 4","campaign_id":"120242102289220620","campaign_name":"[JOINVILLE S DO SUL + S BENTO DO SUL] - [VALIDAÇAO CRIATIVO]","adset":"","thumbnail":"https://scontent-lhr8-2.xx.fbcdn.net/v/t15.5256-10/661622675_2196644494413136_527894818776434001_n.jpg?_nc_cat=101&ccb=1-7&_nc_ohc=BxbijmGk2h4Q7kNvwFVPOLg&_nc_oc=Adr-ilSUuyyTdwU_zxlUqE6MPLv9oJmhyjA9IvwNv5olQteH0Z4UAUPDmzv34-vdpPY&_nc_zt=23&_nc_ht=scontent-lhr8-2.xx&edm=AOgd6ZUEAAAA&_nc_gid=f2mTQQnWU4Aozu9icrgzMQ&_nc_tpa=Q5bMBQE47c2ybROieVZW2PWwxOsaCsNSidlHi6I_Rc_Qz2UzV13pXpIdeGYs3fq-z2HiCjxQ9dCA0rDdvA&stp=c0.5000x0.5000f_dst-emg0_p64x64_q75_tt6&ur=5fad0e&_nc_sid=58080a&oh=00_Af7zwNuiIOSxjXF--TI4_cuDsEZcWZBTws6ui1LiX2-rew&oe=6A162AC4","preview_url":"https://business.facebook.com/ads/api/preview_iframe.php?d=AQJd3XCd-gIwlOBh1dvBuYCuGwGN-qJd2oPiA1lI8mc3FtYIeJh6oVCF6g31UOOb7RhaqANBqIiTH9F4XXtYRvrc1KqMYlJqEtMJyoHvwrjeAaNz5RAn92qO0U2So1XFnTSYoUb5dUzSUzTDAdXZSahCu3z2tBO6Nvh8JdT8bEFwcV_kfMffMdZZCQcKY8N1og5nL-bydhHIe4laZJYGlCFoIz9vcHHWYyx43aS9qI_sLNdaqdGTtzK1VLkT2_wuyc6qoNRRudpce_pJleGXMHGeFJ7VE6ZY1RNEXgAJbQSRC0E0WB0JAf2zH-giUuyaq5NVUl9DsdbXfZxt9Off63Z4MCImVttZnrNiLW-FUmTer6lUyDgi5L6jM81P2JvzmPJNIkuLchfKwjYcMwk9FYTkaIsm9tyelg-ybhwtgJCSmBG6oeaWIkobWjkEmTFX7G8&t=AQIJhk2QCer87Gx_2q4","active":true,"msgs":0,"leads":1,"purchases":0,"add_to_cart":0,"initiate_checkout":0,"lpv":0,"link_clicks":3,"cp_msg":0,"cpl":4.31,"cpv":0,"spend":4.31,"impressions":185,"cpm":23.3,"ctr":2.7},{"id":"120242102462690620","name":"CRIATIVO 2","campaign_id":"120242102289220620","campaign_name":"[JOINVILLE S DO SUL + S BENTO DO SUL] - [VALIDAÇAO CRIATIVO]","adset":"","thumbnail":"https://scontent-lhr8-1.xx.fbcdn.net/v/t15.5256-10/660506636_947102857966066_4451941496453873501_n.jpg?_nc_cat=107&ccb=1-7&_nc_ohc=ObplQ5qmUTwQ7kNvwFChgRs&_nc_oc=AdplgdrasZ84CSIoLx2KUazHoxQSV3xr5xxxTG8VJTHodGYUvd0QgrfhnIsJUk4K50g&_nc_zt=23&_nc_ht=scontent-lhr8-1.xx&edm=AOgd6ZUEAAAA&_nc_gid=f2mTQQnWU4Aozu9icrgzMQ&_nc_tpa=Q5bMBQENaioxG4x0ff07DXj1oNh00x6FzQ6t9tdB6p_w1pxJ3d2yjP_45Rbq2xTJ-boFYcgntRKPGfeOBw&stp=c0.5000x0.5000f_dst-emg0_p64x64_q75_tt6&ur=5fad0e&_nc_sid=58080a&oh=00_Af7u33AxRFZ1vXgtoaRY7dkQSrT2bwXF3pDFcLolF4xvaA&oe=6A16290F","preview_url":"https://business.facebook.com/ads/api/preview_iframe.php?d=AQJrcFOURlp-qcsjDu6uRmEe9xAsao9z6qWPEnKm3nPQofeavgqDScXF7hKfb894hbW3d1Kno91SCnFX4WBukdRtQDdd5unsc-07Gu9drWs2mr4UiN6NGMliVk8hojk5-AvR-A9SXPnSzLRIgN_ljIFEJLoIJ3zGDkGXUjriQjMkD5bULOHGDWGdNrdai9kL3DqQjgt0De4uK_6023FVvKnt5reSzQqnjfez5monxZSL-KXWAF3GtEBFWwgnlpgxjMNH1Lux1IUnrPytw5j_wfYewlGecFD-kQjMap8nLJQGYOEjFqgC6hO2hBgoJadgck8P8P2lyGh3QvyiM0KgfWlqHKiJRYzu-_GVE2eC2BOrFqrHbWCUkfPgaHpFA1tBRCqKLI2o34GUyolPGP9e9DudCCZCSPHedHbWkoLZZudUYEz-wlKMZ9Ou1JAcxVOyy1E&t=AQLV7kcbizUIdVXSZO4","active":true,"msgs":0,"leads":1,"purchases":0,"add_to_cart":0,"initiate_checkout":0,"lpv":0,"link_clicks":3,"cp_msg":0,"cpl":2.7,"cpv":0,"spend":2.7,"impressions":119,"cpm":22.69,"ctr":3.36},{"id":"120242102462700620","name":"CRIATIVO 1","campaign_id":"120242102289220620","campaign_name":"[JOINVILLE S DO SUL + S BENTO DO SUL] - [VALIDAÇAO CRIATIVO]","adset":"","thumbnail":"https://scontent-lhr6-1.xx.fbcdn.net/v/t15.5256-10/657761166_1621105062345134_1597962393512026482_n.jpg?_nc_cat=110&ccb=1-7&_nc_ohc=51ACGx8fpmYQ7kNvwEeV-2A&_nc_oc=AdoD0tvhuo6UXDAp-sZf4l0aXu5clcb4wBxibx8llIgP0U_HAs3YlydQ_9r56YeWFAE&_nc_zt=23&_nc_ht=scontent-lhr6-1.xx&edm=AOgd6ZUEAAAA&_nc_gid=f2mTQQnWU4Aozu9icrgzMQ&_nc_tpa=Q5bMBQEeApgHNExCGWT3hcBzqV-MSgS3M9s-DR7En34zRzwJWwJzKPIn3A_hxMFt0hofe54Cl30P22hEeg&stp=c0.5000x0.5000f_dst-emg0_p64x64_q75_tt6&ur=5fad0e&_nc_sid=58080a&oh=00_Af562mkt8lvhP-4uRTchQVAUSTaVZ-d2Yf8v0fsymptkQw&oe=6A162988","preview_url":"https://business.facebook.com/ads/api/preview_iframe.php?d=AQKJlr3kGTAQ067JgARXsNzJB3upGqkOYHePgW7ZE7Z9JpRz_sqo_oBwWMjvRN53VpFMaWUEwlZltOtYvQy67K9d0eMb_sCTYrI_DQSET5jICIppVXdw2dxPN6YHsvrI9EBU9cotReo_XPXCBVhURfceSTqG4dCuV-mdRfBGQPoDDnNHSuAUeMmUgEUTU-CW3Euq0TT_Xjye75CoSkc-3BYiY96kzc1S17vrY8oKs3jnajbVMOETH9bFopAnIkXkF6subEyS1PBpHwm2dyr2dgu1sG7zOM99oI5XcvImo2dcb-QD6NAsfQljUvS0GKhG1V9JTwAh3thbikAN34QIBRQACx7fNO-22oE-TPV0_WYCXKtYwDQI59RxbkyWYwxbmlBIGgiYOqtiAw2CY_TCfo-1wZvFWMPRobl2HRlGPLAv9IHDNtlH3gF_CTXjoJojOwU&t=AQISF6VXp28qyAf9oA4","active":true,"msgs":0,"leads":0,"purchases":0,"add_to_cart":0,"initiate_checkout":0,"lpv":0,"link_clicks":0,"cp_msg":0,"cpl":0,"cpv":0,"spend":2.45,"impressions":76,"cpm":32.24,"ctr":0.0},{"id":"120243561192870620","name":"AD REMOLD CÉSAR","campaign_id":"120241197873910620","campaign_name":"[CBO META DE CUSTO] - [LIVE 10 EM 7] - [CRIATIVOS SECUNDÁRIOS]","adset":"","thumbnail":"https://external-lhr6-1.xx.fbcdn.net/emg1/v/t13/5316022775108373689?url=https%3A%2F%2Fwww.facebook.com%2Fads%2Fimage%2F%3Fd%3DAQLkC1ULH73zDLYYBToo0jOKPyaSvJFtVg8TN4qxjMurP2q-sKUW45sCM1kMQXx0nwBFusudiwEQ0JZXGGe63eRANj5HaO-2Tq2UvB1q8NZykNkA4uvsB-ePM5SMbpWvSzRUWmIHIzsYs_b67YgO7iLk&fb_obo=1&utld=facebook.com&stp=c0.5000x0.5000f_dst-emg0_p64x64_q75_tt6&edm=AOgd6ZUEAAAA&_nc_gid=f2mTQQnWU4Aozu9icrgzMQ&_nc_oc=AdohBrtRKvkZI5oz9QUhReG_kD34mQxsyhwd7jIb5fkEH0tK9MMvftZnpQs_vcRnh3I&ccb=13-1&oh=06_Q3-_Ab281R8O4Z7UoXAuuAwH8DZRIcnRYPkpD4uzHO54xWW8&oe=6A123160&_nc_sid=58080a","preview_url":"https://business.facebook.com/ads/api/preview_iframe.php?d=AQIleCegqLUiwaZ3-zOzFth4DB2eT22fL3KjHwmdsHaavL4WlyWSxPLKuZXy9_XDHeTAKMFNFVt3OanuwsJDceu_SyYl5PnDoKt-glhF_Lh-L82-jl-UnrnnFeFYrWGwmfhXcpOgFdfctLZvX418-i0B7CuoZLjLNzLo8v1d9I_Ff35AQfKaLzSs7EBBi_U-BIf9EoSZpnNgo0vuJcvXhlr1pg65v6UrEcRz9Qxcz3dNC_9C4-1PgCX0UIkgI4T4NII_umx6VOJHxUqxduhQH0vqwFWLoADzFOHEOh0lucX6ArXb0ueEdJKdjOOeP6wVx2QeY13Db61W5Pm5T9pUOcTbvCSEkdGBP9hhxVGGBgRM1Vy7qkjg4__aibXbPD2KcH6u90ZRPV9-4ShPT5Y4AnZ66I0IJePjrmHpSipxKZTg9X_la0IWWzydlWA6ApdF8vo&t=AQLbl631X72kxPJS6sU","active":true,"msgs":0,"leads":0,"purchases":0,"add_to_cart":0,"initiate_checkout":0,"lpv":0,"link_clicks":0,"cp_msg":0,"cpl":0,"cpv":0,"spend":0.15,"impressions":3,"cpm":50.0,"ctr":0.0},{"id":"120242286234120620","name":"REMARKETING1","campaign_id":"120241197873910620","campaign_name":"[CBO META DE CUSTO] - [LIVE 10 EM 7] - [CRIATIVOS SECUNDÁRIOS]","adset":"","thumbnail":"https://external-lhr6-1.xx.fbcdn.net/emg1/v/t13/15827226709614646335?url=https%3A%2F%2Fwww.facebook.com%2Fads%2Fimage%2F%3Fd%3DAQKfdrA39lUllgDh4qLfgsLkdN5-Al1itQi37j5GumLJrrH0fo9KzPXjsafr2jRKORG6wXbelEjnYcrBNyXVUdSdWlx3JPWhwQPH4SOB8wUskZkGgDe-P8BzrGKvKhCl5WCPBumDKTiX-7Ms6kdYN6k4&fb_obo=1&utld=facebook.com&stp=c0.5000x0.5000f_dst-emg0_p64x64_q75_tt6&edm=AOgd6ZUEAAAA&_nc_gid=f2mTQQnWU4Aozu9icrgzMQ&_nc_oc=AdoQEY--oaen1KayfLDcaQdh9NwblmXqO-htyTX_bh9Pt7v0_SVW3MPPWR8bGuPa2QE&ccb=13-1&oh=06_Q3-_AWdD8UwF6o9cqi_WyVT7sAHvF2HKyXhqKRQugQG14sM9&oe=6A1232B2&_nc_sid=58080a","preview_url":"https://business.facebook.com/ads/api/preview_iframe.php?d=AQLroDiXUR1hKBoFxBsMoA86TawLUdPDdKTDD92ZAWsDItiNfn4hzmr0H-x1D2k0ZW86of_tqUUrKQnzifO5579AxQuVkS_FaAdaK0cFpR1Y9ZW0tbRg_ZQtCrY-DoW25b4d8wczk4CB681GzJW34j4dEQ8L4YucxFxETMwD1lydhMSh0s8_R27IYiBEvgpArI_MENiSa0MiKy3VUcI4-tYWZa9obz2K9UOhrRILgzmC1iocvRKsTEkGaZfaAdRr79ClqdZU8OWPlqorpP7_0-hx77GZmUwoj3MdOF4FT4GDHfvYGuSAGqrL_MtGO2urbMIAND4RrBFhabTRLU3M2XtJfnzHMdba9Vi-bPvbQKk48wPctHgatZ1oYqFk8w6S_qMotHfSduWLMOd6LQqOGVERRPG0s4Cf2Gfr-HWTVhQy5RwyO2XLcD0r36RCXIVpna8&t=AQK_avpV-riH9jeNdw0","active":true,"msgs":0,"leads":0,"purchases":0,"add_to_cart":0,"initiate_checkout":0,"lpv":0,"link_clicks":0,"cp_msg":0,"cpl":0,"cpv":0,"spend":0.14,"impressions":2,"cpm":70.0,"ctr":0.0}]}